minishell_test/__init__.py
minishell_test/__main__.py
minishell_test/args.py
minishell_test/config.py
minishell_test/hooks.py
minishell_test/sandbox.py
minishell_test/data/__init__.py
minishell_test/data/default.cfg
minishell_test/data/lorem
minishell_test/suite/__init__.py
minishell_test/suite/decorator.py
minishell_test/suite/suite.py
minishell_test/suites/__init__.py
minishell_test/suites/builtin.py
minishell_test/suites/cmd.py
minishell_test/suites/flow.py
minishell_test/suites/misc.py
minishell_test/suites/path.py
minishell_test/suites/preprocess.py
minishell_test/test/__init__.py
minishell_test/test/captured.py
minishell_test/test/result.py
minishell_test/test/test.py
minishell_test-1.1.3.dist-info/LICENSE
minishell_test-1.1.3.dist-info/METADATA
minishell_test-1.1.3.dist-info/WHEEL
minishell_test-1.1.3.dist-info/entry_points.txt
minishell_test-1.1.3.dist-info/top_level.txt
minishell_test-1.1.3.dist-info/RECORD
