Metadata-Version: 2.1
Name: minishell-test
Version: 1.1.3
Summary: test for the minishell project of school 42
Home-page: https://github.com/cacharle/minishell_test
Author: Charles Cabergs
Author-email: me@cacharle.xyz
Maintainer: Charles Cabergs
Maintainer-email: me@cacharle.xyz
License: GPL2
Project-URL: Tracker, https://github.com/cacharle/minishell_test/issues
Platform: UNKNOWN
Classifier: Programming Language :: Python :: 3.6
Classifier: Programming Language :: Python :: 3.7
Classifier: Programming Language :: Python :: 3.8
Classifier: Programming Language :: Python :: 3.9
Classifier: Intended Audience :: Developers
Classifier: Environment :: Console
Classifier: License :: OSI Approved :: GNU General Public License v2 (GPLv2)
Classifier: Operating System :: MacOS
Classifier: Operating System :: POSIX :: Linux
Requires-Python: >=3.6
